thornpy/__init__.py
thornpy/geometry.py
thornpy/numtype.py
thornpy/plotting.py
thornpy/signal.py
thornpy/slideshow.py
thornpy/utilities.py
thornpy/mechanics/__init__.py
thornpy/mechanics/contact.py
thornpy/mechanics/rotation.py
thornpy-0.12.0.dist-info/LICENSE
thornpy-0.12.0.dist-info/METADATA
thornpy-0.12.0.dist-info/WHEEL
thornpy-0.12.0.dist-info/top_level.txt
thornpy-0.12.0.dist-info/RECORD
