Metadata-Version: 2.1
Name: thornpy
Version: 0.12.0
Summary: Miscellaneous Python Tools
Home-page: https://github.com/bthornton191/thornpy
Author: Ben Thornton
Author-email: ben.thornton@mscsoftware.com
Classifier: Programming Language :: Python :: 3
Classifier: License :: OSI Approved :: MIT License
Classifier: Operating System :: Microsoft :: Windows
License-File: LICENSE
Requires-Dist: scipy
Requires-Dist: numpy
Requires-Dist: pandas
Requires-Dist: seaborn
Requires-Dist: matplotlib
Requires-Dist: sympy
